LICENSE
MANIFEST.in
README.md
setup.py
oi/__init__.py
oi/compat.py
oi/core.py
oi/script.py
oi/util.py
oi/version.py
oi/worker.py
oi.egg-info/PKG-INFO
oi.egg-info/SOURCES.txt
oi.egg-info/dependency_links.txt
oi.egg-info/entry_points.txt
oi.egg-info/requires.txt
oi.egg-info/top_level.txt
test/test_oi.py
test/test_util.py