Metadata-Version: 1.1
Name: oi
Version: 0.4.2
Summary: A library for writing long running processes with a cli interface
Home-page: https://github.com/walkr/oi
Author: Tony Walker
Author-email: walkr.walkr@gmail.com
License: MIT
Platform: UNKNOWN
Classifier: License :: OSI Approved :: MIT License
Classifier: Programming Language :: Python
